README.md
setup.py
calpred/__init__.py
calpred/calpred.cli.R
calpred/cli.py
calpred/method.py
calpred/plot.py
calpred/simulate.py
calpred/utils.py
calpred.egg-info/PKG-INFO
calpred.egg-info/SOURCES.txt
calpred.egg-info/dependency_links.txt
calpred.egg-info/entry_points.txt
calpred.egg-info/not-zip-safe
calpred.egg-info/top_level.txt