Metadata-Version: 2.1
Name: calpred
Version: 0.1.1
Summary: calibrated prediction across diverse contexts
